acl2_bridge/__init__.py
acl2_bridge/acl2_bridge.py
acl2_bridge-1.0.dist-info/LICENSE
acl2_bridge-1.0.dist-info/METADATA
acl2_bridge-1.0.dist-info/WHEEL
acl2_bridge-1.0.dist-info/top_level.txt
acl2_bridge-1.0.dist-info/RECORD
